django_telegram_sentry/__init__.py
django_telegram_sentry/apps.py
django_telegram_sentry/handler.py
django_telegram_sentry/tests.py
django_telegram_sentry-1.0.1.dist-info/LICENSE
django_telegram_sentry-1.0.1.dist-info/METADATA
django_telegram_sentry-1.0.1.dist-info/WHEEL
django_telegram_sentry-1.0.1.dist-info/top_level.txt
django_telegram_sentry-1.0.1.dist-info/RECORD
